setup.py
decision_tree/ClassForest.py
decision_tree/ClassTree.py
decision_tree/ClassTreeBagging.py
decision_tree/Examples.py
decision_tree/TreeNode.py
decision_tree/TreeWebRequest.py
decision_tree/__init__.py
decision_tree.egg-info/PKG-INFO
decision_tree.egg-info/SOURCES.txt
decision_tree.egg-info/dependency_links.txt
decision_tree.egg-info/not-zip-safe
decision_tree.egg-info/requires.txt
decision_tree.egg-info/top_level.txt