Metadata-Version: 1.1
Name: decision-tree
Version: 0.04
Summary: Practice implementation of a classification decision tree
Home-page: https://github.com/metjush/decision_tree
Author: metjush
Author-email: metjush@gmail.com
License: MIT
Keywords: classification decision tree machine learning random forest
Platform: UNKNOWN
Classifier: Development Status :: 2 - Pre-Alpha
Classifier: License :: OSI Approved :: MIT License
Classifier: Programming Language :: Python :: 2.7
Classifier: Topic :: Scientific/Engineering :: Artificial Intelligence
